Workbook
Name ActualNumberOfPayments: IFERROR(IF(LoanIsGood,IF(PaymentsPerYear=1,1,MATCH(0.01,End_Bal,-1)+1)),"")
Name ColumnTitle1: #REF!
Name End_Bal: #REF!
Name ExtraPayments: #REF!
Name glide_00ecbaa0b2c84c008d434583999b8a9f: DashBoard!$U$2:$U$2
Name glide_01231e27423a4d19927bf5c0a67d695c: Logbook!$P$1:$P$1
Name glide_016b48bf48e84077ae87d5bbbd13dda4: Logbook!$N$1:$N$1
Name glide_0961cbeebbd842df8840ad9628455d4c: Logbook!$P$1:$P$1
Name glide_0b8e5f95fb7f4dcc99928ecc360daa45: DashBoard!$A$1:$A$1
Name glide_0ebe0973bf69476982dd5f296fa27b28: DashBoard!$U$2:$U$2
Name glide_0f6e0725a29644c1a5f41538835f78b2: Logbook!$P$1:$P$1
Name glide_12cf271462ce44efb12900ad1433627d: Logbook!$P$1:$P$1
Name glide_1479b9e9a41d4bc0a47ca1d570bf1144: Logbook!$O$1:$O$1
Name glide_17544aacabf2444d91d09ed391be1ca4: DashBoard!$R$1:$R$1
Name glide_200fdd3f7b3e403b8ab01ac96c545f21: Logbook!$N$1:$N$1
Name glide_20dd35ea38b049f7b724b8dd45fd8ae6: Logbook!$P$1:$P$1
Name glide_21a1154f2e7e48d296d491f1a2540ed1: Logbook!$H$1:$H$1
Name glide_22e78951478c47f1a6252298c89a55cb: Logbook!$N$1:$N$1
Name glide_2461b56181b845a584c589f7f27a2d84: Logbook!$N$1:$N$1
Name glide_2a8b0c97df3243ec90e94c41f97d97f8: Logbook!$N$1:$N$1
Name glide_2c2aabc9c7904f78b801b8626844a862: Logbook!$N$1:$N$1
Name glide_2cb563fc7d0b4786a010bfe49de51d24: Logbook!$P$1:$P$1
Name glide_2eef8a71e9534310b193a84711c40deb: Logbook!$P$1:$P$1
Name glide_319f432e170d480b904def11ffc733c5: Logbook!$P$1:$P$1
Name glide_32a09c40d73b46e286a56a5762cfaae9: DashBoard!$U$2:$U$2
Name glide_37a84199b6494d1c9b2fea285d8f0c95: Logbook!$Q$1:$Q$1
Name glide_3ba97481672142c0ac5dbb8b02dc8175: Logbook!#REF!
Name glide_3bdbb129c738451ba5266aeb951ecbf3: Logbook!$C$1:$C$1
Name glide_3ff960c061b14cc1801ffbd85dcc311a: DashBoard!$K$1:$K$1
Name glide_4375775089a14cc2b5ee290f31b56b65: Logbook!$P$1:$P$1
Name glide_47dbf5e5ef63471f9bf658476c4dff4e: Logbook!#REF!
Name glide_4f06ccf343e84520ad411c0dfad66254: DashBoard!$E$1:$E$1
Name glide_4f63f1dd00ff42b0a6d24abab7fefeb1: DashBoard!$J$1:$J$1
Name glide_4fd8f42d3a334a7a9b2f904fd08b3964: Logbook!$E$1:$E$1
Name glide_4fdc0d63e2f34daa8fa04a1e156ed65c: Logbook!$B$1:$B$1
Name glide_516d05c4611a4d1c9db73a9e465ba188: DashBoard!$B$1:$B$1
Name glide_579c5faa0945416f9d4922972787ca86: DashBoard!$C$1:$C$1
Name glide_5ac54bb748fc4c50ab9105c9881f337b: DashBoard!$N$1:$N$1
Name glide_5cffb6e9effb4beca41468a35e0573fb: Logbook!$P$1:$P$1
Name glide_60612eb9e63a496ab3a06d96a5a379a0: Logbook!$P$1:$P$1
Name glide_608177821a0c4ca9904aa82a545d60f5: Logbook!$P$1:$P$1
Name glide_610b1770d33044febcbe95eee50d249a: DashBoard!$U$2:$U$2
Name glide_6218e469c0034e6d81c8c7b74532dd63: Logbook!$D$1:$D$1
Name glide_6454d33dc1724e17a4d25bdcc7bb7eee: Logbook!$P$1:$P$1
Name glide_647a73e52b9249c8865b09423401584d: Logbook!$Q$1:$Q$1
Name glide_662525cf860b43cdadcaf44e1b4fcbc6: Logbook!$N$1:$N$1
Name glide_6a8f66c2ec4747e9a3f854d1fb45b496: Logbook!$N$1:$N$1
Name glide_6aa23990460f44e8b3c7680a3aea0aaf: Logbook!$P$1:$P$1
Name glide_6abbfa5c693940d686000f0c5ee08e96: Logbook!$O$1:$O$1
Name glide_6d48afcffd94422d8835b9d1636634ce: DashBoard!$H$1:$H$1
Name glide_71a33385b16d454a90620a5957a478f2: DashBoard!$L$1:$L$1
Name glide_71fb8449560448c18b4f566b6eb4d132: Logbook!$P$1:$P$1
Name glide_7289864bc75543eea1c3ee43f70d5c52: Logbook!$P$1:$P$1
Name glide_759916d5c7f54999b0f873e8e1cb9ae8: Logbook!$N$1:$N$1
Name glide_75a45a97287a443b9c537523dfd61118: Logbook!$P$1:$P$1
Name glide_7767be906adf4ba489025caaf5e5b208: DashBoard!$U$2:$U$2
Name glide_77f0bcdc65d141bab08b640711a365fa: DashBoard!$U$2:$U$2
Name glide_7b1464ce45484f92a3136a78e778a8f6: DashBoard!$O$1:$O$1
Name glide_82be476acfc044399ae2b5eb244b1688: Logbook!$P$1:$P$1
Name glide_83d31ef064f9425bb8f15220fe91005c: Logbook!$N$1:$N$1

Sheet Logbook
A1: month | B1: date | C1: decription | D1: category | E1: income | F1: debit | G1: balance | H1: CREDIT | I1: Notes | J1: February | K1: Total | L1: Projected | M1: Difference
A2: =TEXT(Table2[[#This Row],[date]],"MMMM") -> January | B2: 46023 | C2: Starting Ammount | G2: 4352.3 | J2: Income | K2: =SUMIFS(Table2[[#All],[income]],Table2[[#All],[month]],J1,Table2[[#All],[category]],J2) -> 4084.27 | L2: 10500
A3: =TEXT(Table2[[#This Row],[date]],"MMMM") -> January | B3: 46023 | C3: BJJ | D3: Subscriptions | F3: 100 | G3: =SUM(G2+Table2[[#This Row],[income]]-Table2[[#This Row],[debit]]) -> 4252.3 | J3: Tithe | K3: =SUMIFS(Table2[[#All],[debit]],Table2[[#All],[month]],$J$1,Table2[[#All],[category]],J3) -> 1050 | L3: 1050 | M3: =SUM(L3-K3) -> 0
A4: =TEXT(Table2[[#This Row],[date]],"MMMM") -> January | B4: 46023 | C4: Water and Sewage Raymore | D4: Utilities / Gas / Insurance | F4: 60.41 | G4: =SUM(G3+Table2[[#This Row],[income]]-Table2[[#This Row],[debit]]) -> 4191.89 | J4: House Fund | K4: =SUMIFS(Table2[[#All],[debit]],Table2[[#All],[month]],$J$1,Table2[[#All],[category]],J4) -> 0 | L4: 2100 | M4: =SUM(L4-K4) -> 2100
A5: =TEXT(Table2[[#This Row],[date]],"MMMM") -> January | B5: 46023 | C5: Emma Phone | D5: Utilities / Gas / Insurance | F5: 50 | G5: =SUM(G4+Table2[[#This Row],[income]]-Table2[[#This Row],[debit]]) -> 4141.89 | J5: Retirement | K5: =SUMIFS(Table2[[#All],[debit]],Table2[[#All],[month]],$J$1,Table2[[#All],[category]],J5) -> 0 | L5: 614 | M5: =SUM(L5-K5) -> 614
A6: =TEXT(Table2[[#This Row],[date]],"MMMM") -> January | B6: 46023 | C6: Tithe | D6: Tithe | F6: 1050 | G6: =SUM(G5+Table2[[#This Row],[income]]-Table2[[#This Row],[debit]]) -> 3091.89 | J6: Mortgage | K6: =SUMIFS(Table2[[#All],[debit]],Table2[[#All],[month]],$J$1,Table2[[#All],[category]],J6) -> 2735.72 | L6: 2736 | M6: =SUM(L6-K6) -> 0.28
A7: =TEXT(Table2[[#This Row],[date]],"MMMM") -> January | B7: 46023 | C7: Eric Paycheck | D7: Income | E7: 2033 | G7: =SUM(G6+Table2[[#This Row],[income]]-Table2[[#This Row],[debit]]) -> 5124.89 | J7: Groceries | K7: =SUMIFS(Table2[[#All],[debit]],Table2[[#All],[month]],$J$1,Table2[[#All],[category]],J7) -> 837.75 | L7: 930 | M7: =SUM(L7-K7) -> 92.25
A8: =TEXT(Table2[[#This Row],[date]],"MMMM") -> January | B8: 46024 | C8: T-Mobile | D8: Utilities / Gas / Insurance | F8: 347.5 | G8: =SUM(G7+Table2[[#This Row],[income]]-Table2[[#This Row],[debit]]) -> 4777.39 | J8: Horse Budget | K8: =SUMIFS(Table2[[#All],[debit]],Table2[[#All],[month]],$J$1,Table2[[#All],[category]],J8) -> 531.91 | L8: 870 | M8: =SUM(L8-K8) -> 338.09
A9: =TEXT(Table2[[#This Row],[date]],"MMMM") -> January | B9: 46024 | C9: ALDI | D9: Groceries | F9: 6.33 | G9: =SUM(G8+Table2[[#This Row],[income]]-Table2[[#This Row],[debit]]) -> 4771.06 | J9: Baby Needs | K9: =SUMIFS(Table2[[#All],[debit]],Table2[[#All],[month]],$J$1,Table2[[#All],[category]],J9) -> 81.46 | L9: 500 | M9: =SUM(L9-K9) -> 418.54
A10: =TEXT(Table2[[#This Row],[date]],"MMMM") -> January | B10: 46024 | C10: Sams Club | D10: Groceries | F10: 53.17 | G10: =SUM(G9+Table2[[#This Row],[income]]-Table2[[#This Row],[debit]]) -> 4717.89 | J10: Utilities / Gas / Insurance | K10: =SUMIFS(Table2[[#All],[debit]],Table2[[#All],[month]],$J$1,Table2[[#All],[category]],J10) -> 582.7 | L10: 750 | M10: =SUM(L10-K10) -> 167.3
A11: =TEXT(Table2[[#This Row],[date]],"MMMM") -> January | B11: 46024 | C11: Price Chopper | D11: Groceries | F11: 5.33 | G11: =SUM(G10+Table2[[#This Row],[income]]-Table2[[#This Row],[debit]]) -> 4712.56 | J11: Essentials | K11: =SUMIFS(Table2[[#All],[debit]],Table2[[#All],[month]],$J$1,Table2[[#All],[category]],J11) -> 553.99 | L11: 400 | M11: =SUM(L11-K11) -> -153.99
A12: =TEXT(Table2[[#This Row],[date]],"MMMM") -> January | B12: 46024 | C12: AT&T | D12: Utilities / Gas / Insurance | F12: 90.33 | G12: =SUM(G11+Table2[[#This Row],[income]]-Table2[[#This Row],[debit]]) -> 4622.23 | J12: Subscriptions | K12: =SUMIFS(Table2[[#All],[debit]],Table2[[#All],[month]],$J$1,Table2[[#All],[category]],J12) -> 146.07 | L12: 200 | M12: =SUM(L12-K12) -> 53.93
A13: =TEXT(Table2[[#This Row],[date]],"MMMM") -> January | B13: 46024 | C13: Mortgage | D13: Mortgage | F13: 2735.72 | G13: =SUM(G12+Table2[[#This Row],[income]]-Table2[[#This Row],[debit]]) -> 1886.51 | J13: Dining Out | K13: =SUMIFS(Table2[[#All],[debit]],Table2[[#All],[month]],$J$1,Table2[[#All],[category]],J13) -> 423.44 | L13: 200 | M13: =SUM(L13-K13) -> -223.44
A14: =TEXT(Table2[[#This Row],[date]],"MMMM") -> January | B14: 46026 | C14: Sams Club | D14: Groceries | F14: 25.7 | G14: =SUM(G13+Table2[[#This Row],[income]]-Table2[[#This Row],[debit]]) -> 1860.81 | J14: Entertainment | K14: =SUMIFS(Table2[[#All],[debit]],Table2[[#All],[month]],$J$1,Table2[[#All],[category]],J14) -> 75 | L14: 150 | M14: =SUM(L14-K14) -> 75
A15: =TEXT(Table2[[#This Row],[date]],"MMMM") -> January | B15: 46026 | C15: Amazon - Office/Cable Management | D15: Essentials | F15: 40.21 | G15: =SUM(G14+Table2[[#This Row],[income]]-Table2[[#This Row],[debit]]) -> 1820.6 | K15: =SUMIFS(Table2[[#All],[debit]],Table2[[#All],[month]],$J$1,Table2[[#All],[category]],J15) -> 0 | M15: =SUM(L15-K15) -> 0
A16: =TEXT(Table2[[#This Row],[date]],"MMMM") -> January | B16: 46026 | C16: Price Chopper - Melatonin | D16: Essentials | F16: 9.85 | G16: =SUM(G15+Table2[[#This Row],[income]]-Table2[[#This Row],[debit]]) -> 1810.75 | K16: =SUMIFS(Table2[[#All],[debit]],Table2[[#All],[month]],$J$1,Table2[[#All],[category]],J16) -> 0 | M16: =SUM(L16-K16) -> 0
A17: =TEXT(Table2[[#This Row],[date]],"MMMM") -> January | B17: 46026 | C17: Price Chopper - Groceries | D17: Groceries | F17: 10.12 | G17: =SUM(G16+Table2[[#This Row],[income]]-Table2[[#This Row],[debit]]) -> 1800.63 | K17: =SUMIFS(Table2[[#All],[debit]],Table2[[#All],[month]],$J$1,Table2[[#All],[category]],J17) -> 0 | M17: =SUM(L17-K17) -> 0
A18: =TEXT(Table2[[#This Row],[date]],"MMMM") -> January | B18: 46026 | C18: Gas - Honda | D18: Utilities / Gas / Insurance | F18: 27.04 | G18: =SUM(G17+Table2[[#This Row],[income]]-Table2[[#This Row],[debit]]) -> 1773.59 | K18: =SUMIFS(Table2[[#All],[debit]],Table2[[#All],[month]],$J$1,Table2[[#All],[category]],J18) -> 0
A19: =TEXT(Table2[[#This Row],[date]],"MMMM") -> January | B19: 46026 | C19: Other | D19: Income | E19: 159.73 | G19: =SUM(G18+Table2[[#This Row],[income]]-Table2[[#This Row],[debit]]) -> 1933.32 | I19: Graduation Gift | K19: =SUMIFS(Table2[[#All],[debit]],Table2[[#All],[month]],$J$1,Table2[[#All],[category]],J19) -> 0
A20: =TEXT(Table2[[#This Row],[date]],"MMMM") -> January | B20: 46026 | C20: Bel-Ray Chiropracter CC | D20: Essentials | F20: 32.71 | G20: =SUM(G19+Table2[[#This Row],[income]]-Table2[[#This Row],[debit]]) -> 1900.61 | H20: Paid | J20: TOTAL SPENT | K20: =SUM(K3:K19) -> 7018.04 | L20: =SUM(L3:L19) -> 10500 | M20: =SUM(M3:M19) -> 3481.96
A21: =TEXT(Table2[[#This Row],[date]],"MMMM") -> January | B21: 46028 | C21: Baby Crib | D21: Baby Needs | F21: 247.16 | G21: =SUM(G20+Table2[[#This Row],[income]]-Table2[[#This Row],[debit]]) -> 1653.45
A22: =TEXT(Table2[[#This Row],[date]],"MMMM") -> January | B22: 46028 | C22: Fidelity | D22: Retirement | F22: 614 | G22: =SUM(G21+Table2[[#This Row],[income]]-Table2[[#This Row],[debit]]) -> 1039.45
A23: =TEXT(Table2[[#This Row],[date]],"MMMM") -> January | B23: 46029 | C23: Spire | D23: Utilities / Gas / Insurance | F23: 100.7 | G23: =SUM(G22+Table2[[#This Row],[income]]-Table2[[#This Row],[debit]]) -> 938.75
A24: =TEXT(Table2[[#This Row],[date]],"MMMM") -> January | B24: 46031 | C24: Books | D24: Entertainment | F24: 46.79 | G24: =SUM(G23+Table2[[#This Row],[income]]-Table2[[#This Row],[debit]]) -> 891.96
A25: =TEXT(Table2[[#This Row],[date]],"MMMM") -> January | B25: 46031 | C25: Walmart - Hair Gel | D25: Essentials | F25: 10.77 | G25: =SUM(G24+Table2[[#This Row],[income]]-Table2[[#This Row],[debit]]) -> 881.19
A26: =TEXT(Table2[[#This Row],[date]],"MMMM") -> January | B26: 46031 | C26: Gas Station | D26: Essentials | F26: 30.54 | G26: =SUM(G25+Table2[[#This Row],[income]]-Table2[[#This Row],[debit]]) -> 850.65
A27: =TEXT(Table2[[#This Row],[date]],"MMMM") -> January | B27: 46031 | C27: Target - Deoderant | D27: Essentials | F27: 11 | G27: =SUM(G26+Table2[[#This Row],[income]]-Table2[[#This Row],[debit]]) -> 839.65
A28: =TEXT(Table2[[#This Row],[date]],"MMMM") -> January | B28: 46031 | C28: Emma - Haircut | D28: Essentials | F28: 67 | G28: =SUM(G27+Table2[[#This Row],[income]]-Table2[[#This Row],[debit]]) -> 772.65
A29: =TEXT(Table2[[#This Row],[date]],"MMMM") -> January | B29: 46031 | C29: Marshalls | D29: Essentials | F29: 22.01 | G29: =SUM(G28+Table2[[#This Row],[income]]-Table2[[#This Row],[debit]]) -> 750.64
A30: =TEXT(Table2[[#This Row],[date]],"MMMM") -> January | B30: 46032 | C30: Missouri Mud | D30: Dining Out | F30: 14.3 | G30: =SUM(G29+Table2[[#This Row],[income]]-Table2[[#This Row],[debit]]) -> 736.34
A31: =TEXT(Table2[[#This Row],[date]],"MMMM") -> January | B31: 46032 | C31: Sams Club | D31: Groceries | F31: 54.63 | G31: =SUM(G30+Table2[[#This Row],[income]]-Table2[[#This Row],[debit]]) -> 681.71
A32: =TEXT(Table2[[#This Row],[date]],"MMMM") -> January | B32: 46032 | C32: ALDI | D32: Groceries | F32: 32.7 | G32: =SUM(G31+Table2[[#This Row],[income]]-Table2[[#This Row],[debit]]) -> 649.01
... A43: =TEXT(Table2[[#This Row],[date]],"MMMM") -> January | B43: 46037 | C43: Books | D43: Entertainment | F43: 50 | G43: =SUM(G42+Table2[[#This Row],[income]]-Table2[[#This Row],[debit]]) -> 78.18
A44: =TEXT(Table2[[#This Row],[date]],"MMMM") -> January | B44: 46037 | C44: Eric Paycheck | D44: Income | E44: 2033.53 | G44: =SUM(G43+Table2[[#This Row],[income]]-Table2[[#This Row],[debit]]) -> 2111.71
A45: =TEXT(Table2[[#This Row],[date]],"MMMM") -> January | B45: 46037 | C45: Emma Paycheck | D45: Income | E45: 1911.27 | G45: =SUM(G44+Table2[[#This Row],[income]]-Table2[[#This Row],[debit]]) -> 4022.98
A46: =TEXT(Table2[[#This Row],[date]],"MMMM") -> January | B46: 46037 | C46: Homegoods | D46: Essentials | F46: 19.94 | G46: =SUM(G45+Table2[[#This Row],[income]]-Table2[[#This Row],[debit]]) -> 4003.04
A47: =TEXT(Table2[[#This Row],[date]],"MMMM") -> January | B47: 46038 | C47: Amazon Music | D47: Subscriptions | F47: 5.99 | G47: =SUM(G46+Table2[[#This Row],[income]]-Table2[[#This Row],[debit]]) -> 3997.05
A48: =TEXT(Table2[[#This Row],[date]],"MMMM") -> January | B48: 46038 | C48: Price Chopper | D48: Groceries | F48: 13.15 | G48: =SUM(G47+Table2[[#This Row],[income]]-Table2[[#This Row],[debit]]) -> 3983.9
A49: =TEXT(Table2[[#This Row],[date]],"MMMM") -> January | B49: 46038 | C49: Pan Asia | D49: Dining Out | F49: 39.33 | G49: =SUM(G48+Table2[[#This Row],[income]]-Table2[[#This Row],[debit]]) -> 3944.57
A50: =TEXT(Table2[[#This Row],[date]],"MMMM") -> January | B50: 46038 | C50: Pan Asia | D50: Dining Out | F50: 17.47 | G50: =SUM(G49+Table2[[#This Row],[income]]-Table2[[#This Row],[debit]]) -> 3927.1
A51: =TEXT(Table2[[#This Row],[date]],"MMMM") -> January | B51: 46038 | C51: Gas Honda | D51: Utilities / Gas / Insurance | F51: 26.06 | G51: =SUM(G50+Table2[[#This Row],[income]]-Table2[[#This Row],[debit]]) -> 3901.04
A52: =TEXT(Table2[[#This Row],[date]],"MMMM") -> January | B52: 46038 | C52: Google Cloud CC | D52: Subscriptions | G52: =SUM(G51+Table2[[#This Row],[income]]-Table2[[#This Row],[debit]]) -> 3901.04 | H52: Paid | I52: 1.99
A53: =TEXT(Table2[[#This Row],[date]],"MMMM") -> January | B53: 46039 | C53: Word Fresh MArket | D53: Groceries | F53: 22.71 | G53: =SUM(G52+Table2[[#This Row],[income]]-Table2[[#This Row],[debit]]) -> 3878.33
A54: =TEXT(Table2[[#This Row],[date]],"MMMM") -> January | B54: 46039 | C54: Pan Asia | D54: Dining Out | F54: 15.28 | G54: =SUM(G53+Table2[[#This Row],[income]]-Table2[[#This Row],[debit]]) -> 3863.05
A55: =TEXT(Table2[[#This Row],[date]],"MMMM") -> January | B55: 46039 | C55: Pan Asia | D55: Dining Out | F55: 13.11 | G55: =SUM(G54+Table2[[#This Row],[income]]-Table2[[#This Row],[debit]]) -> 3849.94
A56: =TEXT(Table2[[#This Row],[date]],"MMMM") -> January | B56: 46039 | C56: Pan Asia | D56: Dining Out | F56: 4.71 | G56: =SUM(G55+Table2[[#This Row],[income]]-Table2[[#This Row],[debit]]) -> 3845.23
A57: =TEXT(Table2[[#This Row],[date]],"MMMM") -> January | B57: 46039 | C57: Gas Station | D57: Entertainment | F57: 24.24 | G57: =SUM(G56+Table2[[#This Row],[income]]-Table2[[#This Row],[debit]]) -> 3820.99
A58: =TEXT(Table2[[#This Row],[date]],"MMMM") -> January | B58: 46039 | C58: App | D58: Essentials | F58: 50 | G58: =SUM(G57+Table2[[#This Row],[income]]-Table2[[#This Row],[debit]]) -> 3770.99
A59: =TEXT(Table2[[#This Row],[date]],"MMMM") -> January | B59: 46039 | C59: ALDI | D59: Groceries | F59: 37.42 | G59: =SUM(G58+Table2[[#This Row],[income]]-Table2[[#This Row],[debit]]) -> 3733.57
A60: =TEXT(Table2[[#This Row],[date]],"MMMM") -> January | B60: 46039 | C60: Price Chopper | D60: Groceries | F60: 43.92 | G60: =SUM(G59+Table2[[#This Row],[income]]-Table2[[#This Row],[debit]]) -> 3689.65
A61: =TEXT(Table2[[#This Row],[date]],"MMMM") -> January | B61: 46040 | C61: MArshalls | D61: Essentials | F61: 55.02 | G61: =SUM(G60+Table2[[#This Row],[income]]-Table2[[#This Row],[debit]]) -> 3634.63
A62: =TEXT(Table2[[#This Row],[date]],"MMMM") -> January | B62: 46040 | C62: Amazon | D62: Baby Needs | F62: 86.64 | G62: =SUM(G61+Table2[[#This Row],[income]]-Table2[[#This Row],[debit]]) -> 3547.99
A63: =TEXT(Table2[[#This Row],[date]],"MMMM") -> January | B63: 46040 | C63: Amazon | D63: Baby Needs | F63: 7.74 | G63: =SUM(G62+Table2[[#This Row],[income]]-Table2[[#This Row],[debit]]) -> 3540.25
A64: =TEXT(Table2[[#This Row],[date]],"MMMM") -> January | B64: 46041 | C64: Papa Johns | D64: Dining Out | F64: 18.86 | G64: =SUM(G63+Table2[[#This Row],[income]]-Table2[[#This Row],[debit]]) -> 3521.39
... A70: =TEXT(Table2[[#This Row],[date]],"MMMM") -> January | B70: 46044 | C70: Claude Ai | D70: Subscriptions | F70: 20 | G70: =SUM(G69+Table2[[#This Row],[income]]-Table2[[#This Row],[debit]]) -> 3414.44
A71: =TEXT(Table2[[#This Row],[date]],"MMMM") -> January | B71: 46044 | C71: Bel-Ray Chiropractor CC | D71: Essentials | F71: 34.7 | G71: =SUM(G70+Table2[[#This Row],[income]]-Table2[[#This Row],[debit]]) -> 3379.74 | H71: Paid
A72: =TEXT(Table2[[#This Row],[date]],"MMMM") -> January | B72: 46045 | C72: ALDI | D72: Groceries | F72: 72.03 | G72: =SUM(G71+Table2[[#This Row],[income]]-Table2[[#This Row],[debit]]) -> 3307.71
A73: =TEXT(Table2[[#This Row],[date]],"MMMM") -> January | B73: 46045 | C73: Price Chopper | D73: Groceries | F73: 42.67 | G73: =SUM(G72+Table2[[#This Row],[income]]-Table2[[#This Row],[debit]]) -> 3265.04
A74: =TEXT(Table2[[#This Row],[date]],"MMMM") -> January | B74: 46045 | C74: WINGS | D74: Dining Out | F74: 29.59 | G74: =SUM(G73+Table2[[#This Row],[income]]-Table2[[#This Row],[debit]]) -> 3235.45
A75: =TEXT(Table2[[#This Row],[date]],"MMMM") -> January | B75: 46045 | C75: Steam Game | D75: Entertainment | F75: 25.49 | G75: =SUM(G74+Table2[[#This Row],[income]]-Table2[[#This Row],[debit]]) -> 3209.96
A76: =TEXT(Table2[[#This Row],[date]],"MMMM") -> January | B76: 46047 | C76: Bing | D76: Dining Out | F76: 9.84 | G76: =SUM(G75+Table2[[#This Row],[income]]-Table2[[#This Row],[debit]]) -> 3200.12
A77: =TEXT(Table2[[#This Row],[date]],"MMMM") -> January | B77: 46047 | C77: Sams Club | D77: Groceries | F77: 38.22 | G77: =SUM(G76+Table2[[#This Row],[income]]-Table2[[#This Row],[debit]]) -> 3161.9
A78: =TEXT(Table2[[#This Row],[date]],"MMMM") -> January | B78: 46047 | C78: Amazon | D78: Essentials | F78: 24.57 | G78: =SUM(G77+Table2[[#This Row],[income]]-Table2[[#This Row],[debit]]) -> 3137.33
A79: =TEXT(Table2[[#This Row],[date]],"MMMM") -> January | B79: 46048 | C79: Coffee | D79: Groceries | F79: 3.76 | G79: =SUM(G78+Table2[[#This Row],[income]]-Table2[[#This Row],[debit]]) -> 3133.57
A80: =TEXT(Table2[[#This Row],[date]],"MMMM") -> January | B80: 46048 | C80: HyVee | D80: Groceries | F80: 3.52 | G80: =SUM(G79+Table2[[#This Row],[income]]-Table2[[#This Row],[debit]]) -> 3130.05
A81: =TEXT(Table2[[#This Row],[date]],"MMMM") -> January | B81: 46048 | C81: WholeFoods | D81: Groceries | F81: 29.57 | G81: =SUM(G80+Table2[[#This Row],[income]]-Table2[[#This Row],[debit]]) -> 3100.48
A82: =TEXT(Table2[[#This Row],[date]],"MMMM") -> January | B82: 46048 | C82: Evergy | D82: Utilities / Gas / Insurance | F82: 113.93 | G82: =SUM(G81+Table2[[#This Row],[income]]-Table2[[#This Row],[debit]]) -> 2986.55
A83: =TEXT(Table2[[#This Row],[date]],"MMMM") -> January | B83: 46049 | C83: App | D83: Entertainment | F83: 100 | G83: =SUM(G82+Table2[[#This Row],[income]]-Table2[[#This Row],[debit]]) -> 2886.55
... A88: =TEXT(Table2[[#This Row],[date]],"MMMM") -> January | B88: 46050 | C88: Truck Gas | D88: Utilities / Gas / Insurance | F88: 64.6 | G88: =SUM(G87+Table2[[#This Row],[income]]-Table2[[#This Row],[debit]]) -> 2710.05
A89: =TEXT(Table2[[#This Row],[date]],"MMMM") -> January | B89: 46051 | C89: Disability | D89: Income | E89: 2102.15 | G89: =SUM(G88+Table2[[#This Row],[income]]-Table2[[#This Row],[debit]]) -> 4812.2
A90: =TEXT(Table2[[#This Row],[date]],"MMMM") -> January | B90: 46051 | C90: Disability | D90: Income | E90: 4548.61 | G90: =SUM(G89+Table2[[#This Row],[income]]-Table2[[#This Row],[debit]]) -> 9360.81 | I90: BackPay - Eric Disability
A91: =TEXT(Table2[[#This Row],[date]],"MMMM") -> January | B91: 46051 | C91: Disability | D91: Income | E91: 552.47 | G91: =SUM(G90+Table2[[#This Row],[income]]-Table2[[#This Row],[debit]]) -> 9913.28
A92: =TEXT(Table2[[#This Row],[date]],"MMMM") -> January | B92: 46051 | C92: Eric Paycheck | D92: Income | E92: 2033.53 | G92: =SUM(G91+Table2[[#This Row],[income]]-Table2[[#This Row],[debit]]) -> 11946.81
A93: =TEXT(Table2[[#This Row],[date]],"MMMM") -> January | B93: 46051 | C93: Emma Paycheck | D93: Income | E93: 1911.26 | G93: =SUM(G92+Table2[[#This Row],[income]]-Table2[[#This Row],[debit]]) -> 13858.07
A94: =TEXT(Table2[[#This Row],[date]],"MMMM") -> January | B94: 46052 | C94: Bakery | D94: Groceries | F94: 38.54 | G94: =SUM(G93+Table2[[#This Row],[income]]-Table2[[#This Row],[debit]]) -> 13819.53
A95: =TEXT(Table2[[#This Row],[date]],"MMMM") -> January | B95: 46052 | C95: Target | D95: Baby Needs | F95: 60.46 | G95: =SUM(G94+Table2[[#This Row],[income]]-Table2[[#This Row],[debit]]) -> 13759.07
A96: =TEXT(Table2[[#This Row],[date]],"MMMM") -> January | B96: 46052 | C96: T Mobile Emma's Phone | D96: Utilities / Gas / Insurance | F96: 110.98 | G96: =SUM(G95+Table2[[#This Row],[income]]-Table2[[#This Row],[debit]]) -> 13648.09
A97: =TEXT(Table2[[#This Row],[date]],"MMMM") -> January | B97: 46052 | C97: Price Chopper - Wings | D97: Groceries | F97: 16.44 | G97: =SUM(G96+Table2[[#This Row],[income]]-Table2[[#This Row],[debit]]) -> 13631.65
A98: =TEXT(Table2[[#This Row],[date]],"MMMM") -> January | B98: 46053 | C98: Bing Coffee | D98: Groceries | F98: 1.49 | G98: =SUM(G97+Table2[[#This Row],[income]]-Table2[[#This Row],[debit]]) -> 13630.16
A99: =TEXT(Table2[[#This Row],[date]],"MMMM") -> January | B99: 46053 | C99: ALDI | D99: Groceries | F99: 57.73 | G99: =SUM(G98+Table2[[#This Row],[income]]-Table2[[#This Row],[debit]]) -> 13572.43
A100: =TEXT(Table2[[#This Row],[date]],"MMMM") -> January | B100: 46053 | C100: Dividend | D100: Income | E100: 0.21 | G100: =SUM(G99+Table2[[#This Row],[income]]-Table2[[#This Row],[debit]]) -> 13572.64
A101: =TEXT(Table2[[#This Row],[date]],"MMMM") -> January | B101: 46053 | C101: Other | D101: Income | E101: 187.16 | G101: =SUM(G100+Table2[[#This Row],[income]]-Table2[[#This Row],[debit]]) -> 13759.8
A102: =TEXT(Table2[[#This Row],[date]],"MMMM") -> January | B102: 46053 | C102: Microsoft | D102: Subscriptions | F102: 109.46 | G102: =SUM(G101+Table2[[#This Row],[income]]-Table2[[#This Row],[debit]]) -> 13650.34
A103: =TEXT(Table2[[#This Row],[date]],"MMMM") -> January | B103: 46053 | C103: House Fund | D103: House Fund | F103: 2100 | G103: =SUM(G102+Table2[[#This Row],[income]]-Table2[[#This Row],[debit]]) -> 11550.34
A104: =TEXT(Table2[[#This Row],[date]],"MMMM") -> February | B104: 46054 | C104: Tithe | D104: Tithe | F104: 792 | G104: =SUM(G103+Table2[[#This Row],[income]]-Table2[[#This Row],[debit]]) -> 10758.34
A105: =TEXT(Table2[[#This Row],[date]],"MMMM") -> February | B105: 46054 | C105: Tithe | D105: Tithe | F105: 258 | G105: =SUM(G104+Table2[[#This Row],[income]]-Table2[[#This Row],[debit]]) -> 10500.34
A106: =TEXT(Table2[[#This Row],[date]],"MMMM") -> February | B106: 46054 | C106: Mortgage | D106: Mortgage | F106: 2735.72 | G106: =SUM(G105+Table2[[#This Row],[income]]-Table2[[#This Row],[debit]]) -> 7764.62
A107: =TEXT(Table2[[#This Row],[date]],"MMMM") -> February | B107: 46054 | C107: SAVINGS! | D107: SAVINGS! | F107: 6000 | G107: =SUM(G106+Table2[[#This Row],[income]]-Table2[[#This Row],[debit]]) -> 1764.62
A108: =TEXT(Table2[[#This Row],[date]],"MMMM") -> February | B108: 46054 | C108: BJJ | D108: Subscriptions | F108: 100 | G108: =SUM(G107+Table2[[#This Row],[income]]-Table2[[#This Row],[debit]]) -> 1664.62
A109: =TEXT(Table2[[#This Row],[date]],"MMMM") -> February | B109: 46054 | C109: Water and Sewage Raymore | D109: Utilities / Gas / Insurance | F109: 60.41 | G109: =SUM(G108+Table2[[#This Row],[income]]-Table2[[#This Row],[debit]]) -> 1604.21
A110: =TEXT(Table2[[#This Row],[date]],"MMMM") -> February | B110: 46054 | C110: Baby Shower Gift | D110: Essentials | F110: 52.58 | G110: =SUM(G109+Table2[[#This Row],[income]]-Table2[[#This Row],[debit]]) -> 1551.63
A111: =TEXT(Table2[[#This Row],[date]],"MMMM") -> February | B111: 46054 | C111: Pan Asia - Food | D111: Dining Out | F111: 44.79 | G111: =SUM(G110+Table2[[#This Row],[income]]-Table2[[#This Row],[debit]]) -> 1506.84
A112: =TEXT(Table2[[#This Row],[date]],"MMMM") -> February | B112: 46054 | C112: Pan Asia - Drinks | D112: Dining Out | F112: 15.29 | G112: =SUM(G111+Table2[[#This Row],[income]]-Table2[[#This Row],[debit]]) -> 1491.55
A113: =TEXT(Table2[[#This Row],[date]],"MMMM") -> February | B113: 46055 | C113: Amazon | D113: Essentials | F113: 33.72 | G113: =SUM(G112+Table2[[#This Row],[income]]-Table2[[#This Row],[debit]]) -> 1457.83
... A116: =TEXT(Table2[[#This Row],[date]],"MMMM") -> February | B116: 46056 | C116: Sams Club | D116: Groceries | F116: 20.66 | G116: =SUM(G115+Table2[[#This Row],[income]]-Table2[[#This Row],[debit]]) -> 1411.9
A117: =TEXT(Table2[[#This Row],[date]],"MMMM") -> February | B117: 46056 | C117: Bel-Ray Chiropractor CC | D117: Essentials | F117: 32.71 | G117: =SUM(G116+Table2[[#This Row],[income]]-Table2[[#This Row],[debit]]) -> 1379.19 | H117: Paid
A118: =TEXT(Table2[[#This Row],[date]],"MMMM") -> February | B118: 46056 | C118: AT&T | D118: Utilities / Gas / Insurance | F118: 90.33 | G118: =SUM(G117+Table2[[#This Row],[income]]-Table2[[#This Row],[debit]]) -> 1288.86
A119: =TEXT(Table2[[#This Row],[date]],"MMMM") -> February | B119: 46057 | C119: Smoothie | D119: Dining Out | F119: 19.15 | G119: =SUM(G118+Table2[[#This Row],[income]]-Table2[[#This Row],[debit]]) -> 1269.71
A120: =TEXT(Table2[[#This Row],[date]],"MMMM") -> February | B120: 46057 | C120: Emma Phone (Last Transfer 2 Dad) | D120: Utilities / Gas / Insurance | F120: 50 | G120: =SUM(G119+Table2[[#This Row],[income]]-Table2[[#This Row],[debit]]) -> 1219.71
A121: =TEXT(Table2[[#This Row],[date]],"MMMM") -> February | B121: 46057 | C121: Target Gifts | D121: Groceries | F121: 34.19 | G121: =SUM(G120+Table2[[#This Row],[income]]-Table2[[#This Row],[debit]]) -> 1185.52
...

Sheet DashBoard
B2: Month To Date | G2: Year To Date
B3: Month | C3: February
B4: Income | C4: Total | D4: Budgeted | E4: Vs Budget | G4: January | H4: February | I4: March | J4: April | K4: May | L4: June | M4: July | N4: August | O4: September | P4: October | Q4: November | R4: December | S4: Total
B5: Eric Paycheck | C5: =SUMIFS(Logbook!E$1:E$696, Logbook!A$1:A$696, DashBoard!$C$3, Logbook!C$1:C$696, DashBoard!B5) -> 2033 | D5: 4066 | E5: 0 | G5: =SUMIFS(Logbook!$E$1:$E$696,Logbook!$A$1:$A$696,DashBoard!G$4,Logbook!$C$1:$C$696,DashBoard!$B5) -> 6100.06 | H5: =SUMIFS(Logbook!$E$1:$E$696,Logbook!$A$1:$A$696,DashBoard!H$4,Logbook!$C$1:$C$696,DashBoard!$B5) -> 2033 | I5: =SUMIFS(Logbook!$E$1:$E$696,Logbook!$A$1:$A$696,DashBoard!I$4,Logbook!$C$1:$C$696,DashBoard!$B5) -> 0 | J5: =SUMIFS(Logbook!$E$1:$E$696,Logbook!$A$1:$A$696,DashBoard!J$4,Logbook!$C$1:$C$696,DashBoard!$B5) -> 0 | K5: =SUMIFS(Logbook!$E$1:$E$696,Logbook!$A$1:$A$696,DashBoard!K$4,Logbook!$C$1:$C$696,DashBoard!$B5) -> 0 | L5: =SUMIFS(Logbook!$E$1:$E$696,Logbook!$A$1:$A$696,DashBoard!L$4,Logbook!$C$1:$C$696,DashBoard!$B5) -> 0 | M5: =SUMIFS(Logbook!$E$1:$E$696,Logbook!$A$1:$A$696,DashBoard!M$4,Logbook!$C$1:$C$696,DashBoard!$B5) -> 0 | N5: =SUMIFS(Logbook!$E$1:$E$696,Logbook!$A$1:$A$696,DashBoard!N$4,Logbook!$C$1:$C$696,DashBoard!$B5) -> 0 | ... R5: =SUMIFS(Logbook!$E$1:$E$696,Logbook!$A$1:$A$696,DashBoard!R$4,Logbook!$C$1:$C$696,DashBoard!$B5) -> 0 | S5: =SUM(G5:R5) -> 8133.06
B6: Emma Paycheck | C6: =SUMIFS(Logbook!E$1:E$696, Logbook!A$1:A$696, DashBoard!$C$3, Logbook!C$1:C$696, DashBoard!B6) -> 1911.27 | D6: 3822.54 | E6: 0 | G6: =SUMIFS(Logbook!$E$1:$E$696,Logbook!$A$1:$A$696,DashBoard!G$4,Logbook!$C$1:$C$696,DashBoard!$B6) -> 3822.53 | H6: =SUMIFS(Logbook!$E$1:$E$696,Logbook!$A$1:$A$696,DashBoard!H$4,Logbook!$C$1:$C$696,DashBoard!$B6) -> 1911.27 | I6: =SUMIFS(Logbook!$E$1:$E$696,Logbook!$A$1:$A$696,DashBoard!I$4,Logbook!$C$1:$C$696,DashBoard!$B6) -> 0 | J6: =SUMIFS(Logbook!$E$1:$E$696,Logbook!$A$1:$A$696,DashBoard!J$4,Logbook!$C$1:$C$696,DashBoard!$B6) -> 0 | K6: =SUMIFS(Logbook!$E$1:$E$696,Logbook!$A$1:$A$696,DashBoard!K$4,Logbook!$C$1:$C$696,DashBoard!$B6) -> 0 | L6: =SUMIFS(Logbook!$E$1:$E$696,Logbook!$A$1:$A$696,DashBoard!L$4,Logbook!$C$1:$C$696,DashBoard!$B6) -> 0 | M6: =SUMIFS(Logbook!$E$1:$E$696,Logbook!$A$1:$A$696,DashBoard!M$4,Logbook!$C$1:$C$696,DashBoard!$B6) -> 0 | N6: =SUMIFS(Logbook!$E$1:$E$696,Logbook!$A$1:$A$696,DashBoard!N$4,Logbook!$C$1:$C$696,DashBoard!$B6) -> 0 | ... R6: =SUMIFS(Logbook!$E$1:$E$696,Logbook!$A$1:$A$696,DashBoard!R$4,Logbook!$C$1:$C$696,DashBoard!$B6) -> 0 | S6: =SUM(G6:R6) -> 5733.8
B7: Disability | C7: =SUMIFS(Logbook!E$1:E$696, Logbook!A$1:A$696, DashBoard!$C$3, Logbook!C$1:C$696, DashBoard!B7) -> 0 | D7: 2654.62 | E7: 0 | G7: =SUMIFS(Logbook!$E$1:$E$696,Logbook!$A$1:$A$696,DashBoard!G$4,Logbook!$C$1:$C$696,DashBoard!$B7) -> 7203.23 | H7: =SUMIFS(Logbook!$E$1:$E$696,Logbook!$A$1:$A$696,DashBoard!H$4,Logbook!$C$1:$C$696,DashBoard!$B7) -> 0 | I7: =SUMIFS(Logbook!$E$1:$E$696,Logbook!$A$1:$A$696,DashBoard!I$4,Logbook!$C$1:$C$696,DashBoard!$B7) -> 0 | J7: =SUMIFS(Logbook!$E$1:$E$696,Logbook!$A$1:$A$696,DashBoard!J$4,Logbook!$C$1:$C$696,DashBoard!$B7) -> 0 | K7: =SUMIFS(Logbook!$E$1:$E$696,Logbook!$A$1:$A$696,DashBoard!K$4,Logbook!$C$1:$C$696,DashBoard!$B7) -> 0 | L7: =SUMIFS(Logbook!$E$1:$E$696,Logbook!$A$1:$A$696,DashBoard!L$4,Logbook!$C$1:$C$696,DashBoard!$B7) -> 0 | M7: =SUMIFS(Logbook!$E$1:$E$696,Logbook!$A$1:$A$696,DashBoard!M$4,Logbook!$C$1:$C$696,DashBoard!$B7) -> 0 | N7: =SUMIFS(Logbook!$E$1:$E$696,Logbook!$A$1:$A$696,DashBoard!N$4,Logbook!$C$1:$C$696,DashBoard!$B7) -> 0 | ... R7: =SUMIFS(Logbook!$E$1:$E$696,Logbook!$A$1:$A$696,DashBoard!R$4,Logbook!$C$1:$C$696,DashBoard!$B7) -> 0 | S7: =SUM(G7:R7) -> 7203.23
B8: Dividend | C8: =SUMIFS(Logbook!E$1:E$696, Logbook!A$1:A$696, DashBoard!$C$3, Logbook!C$1:C$696, DashBoard!B8) -> 0 | D8: 0 | E8: 0 | G8: =SUMIFS(Logbook!$E$1:$E$696,Logbook!$A$1:$A$696,DashBoard!G$4,Logbook!$C$1:$C$696,DashBoard!$B8) -> 0.21 | H8: =SUMIFS(Logbook!$E$1:$E$696,Logbook!$A$1:$A$696,DashBoard!H$4,Logbook!$C$1:$C$696,DashBoard!$B8) -> 0 | I8: =SUMIFS(Logbook!$E$1:$E$696,Logbook!$A$1:$A$696,DashBoard!I$4,Logbook!$C$1:$C$696,DashBoard!$B8) -> 0 | J8: =SUMIFS(Logbook!$E$1:$E$696,Logbook!$A$1:$A$696,DashBoard!J$4,Logbook!$C$1:$C$696,DashBoard!$B8) -> 0 | K8: =SUMIFS(Logbook!$E$1:$E$696,Logbook!$A$1:$A$696,DashBoard!K$4,Logbook!$C$1:$C$696,DashBoard!$B8) -> 0 | L8: =SUMIFS(Logbook!$E$1:$E$696,Logbook!$A$1:$A$696,DashBoard!L$4,Logbook!$C$1:$C$696,DashBoard!$B8) -> 0 | M8: =SUMIFS(Logbook!$E$1:$E$696,Logbook!$A$1:$A$696,DashBoard!M$4,Logbook!$C$1:$C$696,DashBoard!$B8) -> 0 | N8: =SUMIFS(Logbook!$E$1:$E$696,Logbook!$A$1:$A$696,DashBoard!N$4,Logbook!$C$1:$C$696,DashBoard!$B8) -> 0 | ... R8: =SUMIFS(Logbook!$E$1:$E$696,Logbook!$A$1:$A$696,DashBoard!R$4,Logbook!$C$1:$C$696,DashBoard!$B8) -> 0
B9: Other | C9: =SUMIFS(Logbook!E$1:E$696, Logbook!A$1:A$696, DashBoard!$C$3, Logbook!C$1:C$696, DashBoard!B9) -> 140 | D9: 0 | E9: 0 | G9: =SUMIFS(Logbook!$E$1:$E$696,Logbook!$A$1:$A$696,DashBoard!G$4,Logbook!$C$1:$C$696,DashBoard!$B9) -> 346.89 | H9: =SUMIFS(Logbook!$E$1:$E$696,Logbook!$A$1:$A$696,DashBoard!H$4,Logbook!$C$1:$C$696,DashBoard!$B9) -> 140 | I9: =SUMIFS(Logbook!$E$1:$E$696,Logbook!$A$1:$A$696,DashBoard!I$4,Logbook!$C$1:$C$696,DashBoard!$B9) -> 0 | J9: =SUMIFS(Logbook!$E$1:$E$696,Logbook!$A$1:$A$696,DashBoard!J$4,Logbook!$C$1:$C$696,DashBoard!$B9) -> 0 | K9: =SUMIFS(Logbook!$E$1:$E$696,Logbook!$A$1:$A$696,DashBoard!K$4,Logbook!$C$1:$C$696,DashBoard!$B9) -> 0 | L9: =SUMIFS(Logbook!$E$1:$E$696,Logbook!$A$1:$A$696,DashBoard!L$4,Logbook!$C$1:$C$696,DashBoard!$B9) -> 0 | M9: =SUMIFS(Logbook!$E$1:$E$696,Logbook!$A$1:$A$696,DashBoard!M$4,Logbook!$C$1:$C$696,DashBoard!$B9) -> 0 | N9: =SUMIFS(Logbook!$E$1:$E$696,Logbook!$A$1:$A$696,DashBoard!N$4,Logbook!$C$1:$C$696,DashBoard!$B9) -> 0 | ... R9: =SUMIFS(Logbook!$E$1:$E$696,Logbook!$A$1:$A$696,DashBoard!R$4,Logbook!$C$1:$C$696,DashBoard!$B9) -> 0 | S9: =SUM(G9:R9) -> 486.89
C10: =SUMIFS(Logbook!E$1:E$696, Logbook!A$1:A$696, DashBoard!$C$3, Logbook!C$1:C$696, DashBoard!B10) -> 0 | D10: 0 | E10: 0 | G10: =SUMIFS(Logbook!$E$1:$E$696,Logbook!$A$1:$A$696,DashBoard!G$4,Logbook!$C$1:$C$696,DashBoard!$B10) -> 0 | H10: =SUMIFS(Logbook!$E$1:$E$696,Logbook!$A$1:$A$696,DashBoard!H$4,Logbook!$C$1:$C$696,DashBoard!$B10) -> 0 | I10: =SUMIFS(Logbook!$E$1:$E$696,Logbook!$A$1:$A$696,DashBoard!I$4,Logbook!$C$1:$C$696,DashBoard!$B10) -> 0 | J10: =SUMIFS(Logbook!$E$1:$E$696,Logbook!$A$1:$A$696,DashBoard!J$4,Logbook!$C$1:$C$696,DashBoard!$B10) -> 0 | K10: =SUMIFS(Logbook!$E$1:$E$696,Logbook!$A$1:$A$696,DashBoard!K$4,Logbook!$C$1:$C$696,DashBoard!$B10) -> 0 | L10: =SUMIFS(Logbook!$E$1:$E$696,Logbook!$A$1:$A$696,DashBoard!L$4,Logbook!$C$1:$C$696,DashBoard!$B10) -> 0 | M10: =SUMIFS(Logbook!$E$1:$E$696,Logbook!$A$1:$A$696,DashBoard!M$4,Logbook!$C$1:$C$696,DashBoard!$B10) -> 0 | N10: =SUMIFS(Logbook!$E$1:$E$696,Logbook!$A$1:$A$696,DashBoard!N$4,Logbook!$C$1:$C$696,DashBoard!$B10) -> 0 | ... R10: =SUMIFS(Logbook!$E$1:$E$696,Logbook!$A$1:$A$696,DashBoard!R$4,Logbook!$C$1:$C$696,DashBoard!$B10) -> 0 | S10: =SUM(G10:R10) -> 0
B11: Total Income | C11: =SUM(C5:C6) -> 3944.27 | D11: =SUM(D5:D7) -> 10543.16 | E11: =C11 -> 3944.27 | G11: =SUM(G5:G10) -> 17472.92 | H11: =SUM(H5:H10) -> 4084.27 | I11: =SUM(I5:I10) -> 0 | J11: =SUM(J5:J10) -> 0 | K11: =SUM(K5:K10) -> 0 | L11: =SUM(L5:L10) -> 0 | M11: =SUM(M5:M10) -> 0 | N11: =SUM(N5:N10) -> 0 | ... R11: =SUM(R5:R10) -> 0 | S11: =SUM(G11:R11) -> 21557.19
B12: Debit | C12: Total | D12: Budgeted | E12: Vs Budget
B13: Debit | C13: Total | D13: Budgeted | E13: Vs Budget | G13: January | H13: February | I13: March | J13: April | K13: May | L13: June | M13: July | N13: August | O13: September | P13: October | Q13: November | R13: December | S13: Total
B14: Tithe | C14: =SUMIFS(Logbook!$F$1:$F$696,Logbook!$A$1:$A$696,DashBoard!C$3,Logbook!$D$1:$D$696,DashBoard!$B14) -> 1050 | D14: 1050 | E14: =SUM(D14-C14) -> 0 | G14: =SUMIFS(Logbook!$F$1:$F$696,Logbook!$A$1:$A$696,DashBoard!G$4,Logbook!$D$1:$D$696,DashBoard!$B14) -> 1050 | H14: =SUMIFS(Logbook!$F$1:$F$696,Logbook!$A$1:$A$696,DashBoard!H$4,Logbook!$D$1:$D$696,DashBoard!$B14) -> 1050 | I14: =SUMIFS(Logbook!$F$1:$F$696,Logbook!$A$1:$A$696,DashBoard!I$4,Logbook!$D$1:$D$696,DashBoard!$B14) -> 0 | J14: =SUMIFS(Logbook!$F$1:$F$696,Logbook!$A$1:$A$696,DashBoard!J$4,Logbook!$D$1:$D$696,DashBoard!$B14) -> 0 | K14: =SUMIFS(Logbook!$F$1:$F$696,Logbook!$A$1:$A$696,DashBoard!K$4,Logbook!$D$1:$D$696,DashBoard!$B14) -> 0 | L14: =SUMIFS(Logbook!$F$1:$F$696,Logbook!$A$1:$A$696,DashBoard!L$4,Logbook!$D$1:$D$696,DashBoard!$B14) -> 0 | M14: =SUMIFS(Logbook!$F$1:$F$696,Logbook!$A$1:$A$696,DashBoard!M$4,Logbook!$D$1:$D$696,DashBoard!$B14) -> 0 | N14: =SUMIFS(Logbook!$F$1:$F$696,Logbook!$A$1:$A$696,DashBoard!N$4,Logbook!$D$1:$D$696,DashBoard!$B14) -> 0 | ... R14: =SUMIFS(Logbook!$F$1:$F$696,Logbook!$A$1:$A$696,DashBoard!R$4,Logbook!$D$1:$D$696,DashBoard!$B14) -> 0 | S14: =SUM(G14:R14) -> 2100
B15: House Fund | C15: =SUMIFS(Logbook!F$1:F$696,Logbook!A$1:A$696,DashBoard!$C$3,Logbook!D$1:D$696,DashBoard!B15) -> 0 | D15: 2100 | E15: =SUM(D15-C15) -> 2100 | G15: =SUMIFS(Logbook!$F$1:$F$696,Logbook!$A$1:$A$696,DashBoard!G$4,Logbook!$D$1:$D$696,DashBoard!$B15) -> 2100 | H15: =SUMIFS(Logbook!$F$1:$F$696,Logbook!$A$1:$A$696,DashBoard!H$4,Logbook!$D$1:$D$696,DashBoard!$B15) -> 0 | I15: =SUMIFS(Logbook!$F$1:$F$696,Logbook!$A$1:$A$696,DashBoard!I$4,Logbook!$D$1:$D$696,DashBoard!$B15) -> 0 | J15: =SUMIFS(Logbook!$F$1:$F$696,Logbook!$A$1:$A$696,DashBoard!J$4,Logbook!$D$1:$D$696,DashBoard!$B15) -> 0 | K15: =SUMIFS(Logbook!$F$1:$F$696,Logbook!$A$1:$A$696,DashBoard!K$4,Logbook!$D$1:$D$696,DashBoard!$B15) -> 0 | L15: =SUMIFS(Logbook!$F$1:$F$696,Logbook!$A$1:$A$696,DashBoard!L$4,Logbook!$D$1:$D$696,DashBoard!$B15) -> 0 | M15: =SUMIFS(Logbook!$F$1:$F$696,Logbook!$A$1:$A$696,DashBoard!M$4,Logbook!$D$1:$D$696,DashBoard!$B15) -> 0 | N15: =SUMIFS(Logbook!$F$1:$F$696,Logbook!$A$1:$A$696,DashBoard!N$4,Logbook!$D$1:$D$696,DashBoard!$B15) -> 0 | ... R15: =SUMIFS(Logbook!$F$1:$F$696,Logbook!$A$1:$A$696,DashBoard!R$4,Logbook!$D$1:$D$696,DashBoard!$B15) -> 0 | S15: =SUM(G15:R15) -> 2100
B16: Retirement | C16: =SUMIFS(Logbook!F$1:F$696,Logbook!A$1:A$696,DashBoard!$C$3,Logbook!D$1:D$696,DashBoard!B16) -> 0 | D16: 614 | E16: =SUM(D16-C16) -> 614 | G16: =SUMIFS(Logbook!$F$1:$F$696,Logbook!$A$1:$A$696,DashBoard!G$4,Logbook!$D$1:$D$696,DashBoard!$B16) -> 614 | H16: =SUMIFS(Logbook!$F$1:$F$696,Logbook!$A$1:$A$696,DashBoard!H$4,Logbook!$D$1:$D$696,DashBoard!$B16) -> 0 | I16: =SUMIFS(Logbook!$F$1:$F$696,Logbook!$A$1:$A$696,DashBoard!I$4,Logbook!$D$1:$D$696,DashBoard!$B16) -> 0 | J16: =SUMIFS(Logbook!$F$1:$F$696,Logbook!$A$1:$A$696,DashBoard!J$4,Logbook!$D$1:$D$696,DashBoard!$B16) -> 0 | K16: =SUMIFS(Logbook!$F$1:$F$696,Logbook!$A$1:$A$696,DashBoard!K$4,Logbook!$D$1:$D$696,DashBoard!$B16) -> 0 | L16: =SUMIFS(Logbook!$F$1:$F$696,Logbook!$A$1:$A$696,DashBoard!L$4,Logbook!$D$1:$D$696,DashBoard!$B16) -> 0 | M16: =SUMIFS(Logbook!$F$1:$F$696,Logbook!$A$1:$A$696,DashBoard!M$4,Logbook!$D$1:$D$696,DashBoard!$B16) -> 0 | N16: =SUMIFS(Logbook!$F$1:$F$696,Logbook!$A$1:$A$696,DashBoard!N$4,Logbook!$D$1:$D$696,DashBoard!$B16) -> 0 | ... R16: =SUMIFS(Logbook!$F$1:$F$696,Logbook!$A$1:$A$696,DashBoard!R$4,Logbook!$D$1:$D$696,DashBoard!$B16) -> 0 | S16: =SUM(G16:R16) -> 614
B17: Mortgage | C17: =SUMIFS(Logbook!F$1:F$696,Logbook!A$1:A$696,DashBoard!$C$3,Logbook!D$1:D$696,DashBoard!B17) -> 2735.72 | D17: 2736 | E17: =SUM(D17-C17) -> 0.28 | G17: =SUMIFS(Logbook!$F$1:$F$696,Logbook!$A$1:$A$696,DashBoard!G$4,Logbook!$D$1:$D$696,DashBoard!$B17) -> 2735.72 | H17: =SUMIFS(Logbook!$F$1:$F$696,Logbook!$A$1:$A$696,DashBoard!H$4,Logbook!$D$1:$D$696,DashBoard!$B17) -> 2735.72 | I17: =SUMIFS(Logbook!$F$1:$F$696,Logbook!$A$1:$A$696,DashBoard!I$4,Logbook!$D$1:$D$696,DashBoard!$B17) -> 0 | J17: =SUMIFS(Logbook!$F$1:$F$696,Logbook!$A$1:$A$696,DashBoard!J$4,Logbook!$D$1:$D$696,DashBoard!$B17) -> 0 | K17: =SUMIFS(Logbook!$F$1:$F$696,Logbook!$A$1:$A$696,DashBoard!K$4,Logbook!$D$1:$D$696,DashBoard!$B17) -> 0 | L17: =SUMIFS(Logbook!$F$1:$F$696,Logbook!$A$1:$A$696,DashBoard!L$4,Logbook!$D$1:$D$696,DashBoard!$B17) -> 0 | M17: =SUMIFS(Logbook!$F$1:$F$696,Logbook!$A$1:$A$696,DashBoard!M$4,Logbook!$D$1:$D$696,DashBoard!$B17) -> 0 | N17: =SUMIFS(Logbook!$F$1:$F$696,Logbook!$A$1:$A$696,DashBoard!N$4,Logbook!$D$1:$D$696,DashBoard!$B17) -> 0 | ... R17: =SUMIFS(Logbook!$F$1:$F$696,Logbook!$A$1:$A$696,DashBoard!R$4,Logbook!$D$1:$D$696,DashBoard!$B17) -> 0 | S17: =SUM(G17:R17) -> 5471.44
B18: Groceries | C18: =SUMIFS(Logbook!F$1:F$696,Logbook!A$1:A$696,DashBoard!$C$3,Logbook!D$1:D$696,DashBoard!B18) -> 837.75 | D18: 930 | E18: =SUM(D18-C18) -> 92.25 | G18: =SUMIFS(Logbook!$F$1:$F$696,Logbook!$A$1:$A$696,DashBoard!G$4,Logbook!$D$1:$D$696,DashBoard!$B18) -> 672.83 | H18: =SUMIFS(Logbook!$F$1:$F$696,Logbook!$A$1:$A$696,DashBoard!H$4,Logbook!$D$1:$D$696,DashBoard!$B18) -> 837.75 | I18: =SUMIFS(Logbook!$F$1:$F$696,Logbook!$A$1:$A$696,DashBoard!I$4,Logbook!$D$1:$D$696,DashBoard!$B18) -> 0 | J18: =SUMIFS(Logbook!$F$1:$F$696,Logbook!$A$1:$A$696,DashBoard!J$4,Logbook!$D$1:$D$696,DashBoard!$B18) -> 0 | K18: =SUMIFS(Logbook!$F$1:$F$696,Logbook!$A$1:$A$696,DashBoard!K$4,Logbook!$D$1:$D$696,DashBoard!$B18) -> 0 | L18: =SUMIFS(Logbook!$F$1:$F$696,Logbook!$A$1:$A$696,DashBoard!L$4,Logbook!$D$1:$D$696,DashBoard!$B18) -> 0 | M18: =SUMIFS(Logbook!$F$1:$F$696,Logbook!$A$1:$A$696,DashBoard!M$4,Logbook!$D$1:$D$696,DashBoard!$B18) -> 0 | N18: =SUMIFS(Logbook!$F$1:$F$696,Logbook!$A$1:$A$696,DashBoard!N$4,Logbook!$D$1:$D$696,DashBoard!$B18) -> 0 | ... R18: =SUMIFS(Logbook!$F$1:$F$696,Logbook!$A$1:$A$696,DashBoard!R$4,Logbook!$D$1:$D$696,DashBoard!$B18) -> 0 | S18: =SUM(G18:R18) -> 1510.58
B19: Horse Budget | C19: =SUMIFS(Logbook!F$1:F$696,Logbook!A$1:A$696,DashBoard!$C$3,Logbook!D$1:D$696,DashBoard!B19) -> 531.91 | D19: 870 | E19: =SUM(D19-C19) -> 338.09 | G19: =SUMIFS(Logbook!$F$1:$F$696,Logbook!$A$1:$A$696,DashBoard!G$4,Logbook!$D$1:$D$696,DashBoard!$B19) -> 101.34 | H19: =SUMIFS(Logbook!$F$1:$F$696,Logbook!$A$1:$A$696,DashBoard!H$4,Logbook!$D$1:$D$696,DashBoard!$B19) -> 531.91 | I19: =SUMIFS(Logbook!$F$1:$F$696,Logbook!$A$1:$A$696,DashBoard!I$4,Logbook!$D$1:$D$696,DashBoard!$B19) -> 0 | J19: =SUMIFS(Logbook!$F$1:$F$696,Logbook!$A$1:$A$696,DashBoard!J$4,Logbook!$D$1:$D$696,DashBoard!$B19) -> 0 | K19: =SUMIFS(Logbook!$F$1:$F$696,Logbook!$A$1:$A$696,DashBoard!K$4,Logbook!$D$1:$D$696,DashBoard!$B19) -> 0 | L19: =SUMIFS(Logbook!$F$1:$F$696,Logbook!$A$1:$A$696,DashBoard!L$4,Logbook!$D$1:$D$696,DashBoard!$B19) -> 0 | M19: =SUMIFS(Logbook!$F$1:$F$696,Logbook!$A$1:$A$696,DashBoard!M$4,Logbook!$D$1:$D$696,DashBoard!$B19) -> 0 | N19: =SUMIFS(Logbook!$F$1:$F$696,Logbook!$A$1:$A$696,DashBoard!N$4,Logbook!$D$1:$D$696,DashBoard!$B19) -> 0 | ... R19: =SUMIFS(Logbook!$F$1:$F$696,Logbook!$A$1:$A$696,DashBoard!R$4,Logbook!$D$1:$D$696,DashBoard!$B19) -> 0 | S19: =SUM(G19:R19) -> 633.25
B20: Baby Needs | C20: =SUMIFS(Logbook!F$1:F$696,Logbook!A$1:A$696,DashBoard!$C$3,Logbook!D$1:D$696,DashBoard!B20) -> 81.46 | D20: 500 | E20: =SUM(D20-C20) -> 418.54 | G20: =SUMIFS(Logbook!$F$1:$F$696,Logbook!$A$1:$A$696,DashBoard!G$4,Logbook!$D$1:$D$696,DashBoard!$B20) -> 556.17 | H20: =SUMIFS(Logbook!$F$1:$F$696,Logbook!$A$1:$A$696,DashBoard!H$4,Logbook!$D$1:$D$696,DashBoard!$B20) -> 81.46 | I20: =SUMIFS(Logbook!$F$1:$F$696,Logbook!$A$1:$A$696,DashBoard!I$4,Logbook!$D$1:$D$696,DashBoard!$B20) -> 0 | J20: =SUMIFS(Logbook!$F$1:$F$696,Logbook!$A$1:$A$696,DashBoard!J$4,Logbook!$D$1:$D$696,DashBoard!$B20) -> 0 | K20: =SUMIFS(Logbook!$F$1:$F$696,Logbook!$A$1:$A$696,DashBoard!K$4,Logbook!$D$1:$D$696,DashBoard!$B20) -> 0 | L20: =SUMIFS(Logbook!$F$1:$F$696,Logbook!$A$1:$A$696,DashBoard!L$4,Logbook!$D$1:$D$696,DashBoard!$B20) -> 0 | M20: =SUMIFS(Logbook!$F$1:$F$696,Logbook!$A$1:$A$696,DashBoard!M$4,Logbook!$D$1:$D$696,DashBoard!$B20) -> 0 | N20: =SUMIFS(Logbook!$F$1:$F$696,Logbook!$A$1:$A$696,DashBoard!N$4,Logbook!$D$1:$D$696,DashBoard!$B20) -> 0 | ... R20: =SUMIFS(Logbook!$F$1:$F$696,Logbook!$A$1:$A$696,DashBoard!R$4,Logbook!$D$1:$D$696,DashBoard!$B20) -> 0 | S20: =SUM(G20:R20) -> 637.63
B21: Utilities / Gas / Insurance | C21: =SUMIFS(Logbook!F$1:F$696,Logbook!A$1:A$696,DashBoard!$C$3,Logbook!D$1:D$696,DashBoard!B21) -> 582.7 | D21: 750 | E21: =SUM(D21-C21) -> 167.3 | G21: =SUMIFS(Logbook!$F$1:$F$696,Logbook!$A$1:$A$696,DashBoard!G$4,Logbook!$D$1:$D$696,DashBoard!$B21) -> 1114.6 | H21: =SUMIFS(Logbook!$F$1:$F$696,Logbook!$A$1:$A$696,DashBoard!H$4,Logbook!$D$1:$D$696,DashBoard!$B21) -> 582.7 | I21: =SUMIFS(Logbook!$F$1:$F$696,Logbook!$A$1:$A$696,DashBoard!I$4,Logbook!$D$1:$D$696,DashBoard!$B21) -> 0 | J21: =SUMIFS(Logbook!$F$1:$F$696,Logbook!$A$1:$A$696,DashBoard!J$4,Logbook!$D$1:$D$696,DashBoard!$B21) -> 0 | K21: =SUMIFS(Logbook!$F$1:$F$696,Logbook!$A$1:$A$696,DashBoard!K$4,Logbook!$D$1:$D$696,DashBoard!$B21) -> 0 | L21: =SUMIFS(Logbook!$F$1:$F$696,Logbook!$A$1:$A$696,DashBoard!L$4,Logbook!$D$1:$D$696,DashBoard!$B21) -> 0 | M21: =SUMIFS(Logbook!$F$1:$F$696,Logbook!$A$1:$A$696,DashBoard!M$4,Logbook!$D$1:$D$696,DashBoard!$B21) -> 0 | N21: =SUMIFS(Logbook!$F$1:$F$696,Logbook!$A$1:$A$696,DashBoard!N$4,Logbook!$D$1:$D$696,DashBoard!$B21) -> 0 | ... R21: =SUMIFS(Logbook!$F$1:$F$696,Logbook!$A$1:$A$696,DashBoard!R$4,Logbook!$D$1:$D$696,DashBoard!$B21) -> 0 | S21: =SUM(G21:R21) -> 1697.3
B22: Essentials | C22: =SUMIFS(Logbook!F$1:F$696,Logbook!A$1:A$696,DashBoard!$C$3,Logbook!D$1:D$696,DashBoard!B22) -> 553.99 | D22: 400 | E22: =SUM(D22-C22) -> -153.99 | G22: =SUMIFS(Logbook!$F$1:$F$696,Logbook!$A$1:$A$696,DashBoard!G$4,Logbook!$D$1:$D$696,DashBoard!$B22) -> 527.94 | H22: =SUMIFS(Logbook!$F$1:$F$696,Logbook!$A$1:$A$696,DashBoard!H$4,Logbook!$D$1:$D$696,DashBoard!$B22) -> 553.99 | I22: =SUMIFS(Logbook!$F$1:$F$696,Logbook!$A$1:$A$696,DashBoard!I$4,Logbook!$D$1:$D$696,DashBoard!$B22) -> 0 | J22: =SUMIFS(Logbook!$F$1:$F$696,Logbook!$A$1:$A$696,DashBoard!J$4,Logbook!$D$1:$D$696,DashBoard!$B22) -> 0 | K22: =SUMIFS(Logbook!$F$1:$F$696,Logbook!$A$1:$A$696,DashBoard!K$4,Logbook!$D$1:$D$696,DashBoard!$B22) -> 0 | L22: =SUMIFS(Logbook!$F$1:$F$696,Logbook!$A$1:$A$696,DashBoard!L$4,Logbook!$D$1:$D$696,DashBoard!$B22) -> 0 | M22: =SUMIFS(Logbook!$F$1:$F$696,Logbook!$A$1:$A$696,DashBoard!M$4,Logbook!$D$1:$D$696,DashBoard!$B22) -> 0 | N22: =SUMIFS(Logbook!$F$1:$F$696,Logbook!$A$1:$A$696,DashBoard!N$4,Logbook!$D$1:$D$696,DashBoard!$B22) -> 0 | ... R22: =SUMIFS(Logbook!$F$1:$F$696,Logbook!$A$1:$A$696,DashBoard!R$4,Logbook!$D$1:$D$696,DashBoard!$B22) -> 0 | S22: =SUM(G22:R22) -> 1081.93
B23: Subscriptions | C23: =SUMIFS(Logbook!F$1:F$696,Logbook!A$1:A$696,DashBoard!$C$3,Logbook!D$1:D$696,DashBoard!B23) -> 146.07 | D23: 200 | E23: =SUM(D23-C23) -> 53.93 | G23: =SUMIFS(Logbook!$F$1:$F$696,Logbook!$A$1:$A$696,DashBoard!G$4,Logbook!$D$1:$D$696,DashBoard!$B23) -> 289.52 | H23: =SUMIFS(Logbook!$F$1:$F$696,Logbook!$A$1:$A$696,DashBoard!H$4,Logbook!$D$1:$D$696,DashBoard!$B23) -> 146.07 | I23: =SUMIFS(Logbook!$F$1:$F$696,Logbook!$A$1:$A$696,DashBoard!I$4,Logbook!$D$1:$D$696,DashBoard!$B23) -> 0 | J23: =SUMIFS(Logbook!$F$1:$F$696,Logbook!$A$1:$A$696,DashBoard!J$4,Logbook!$D$1:$D$696,DashBoard!$B23) -> 0 | K23: =SUMIFS(Logbook!$F$1:$F$696,Logbook!$A$1:$A$696,DashBoard!K$4,Logbook!$D$1:$D$696,DashBoard!$B23) -> 0 | L23: =SUMIFS(Logbook!$F$1:$F$696,Logbook!$A$1:$A$696,DashBoard!L$4,Logbook!$D$1:$D$696,DashBoard!$B23) -> 0 | M23: =SUMIFS(Logbook!$F$1:$F$696,Logbook!$A$1:$A$696,DashBoard!M$4,Logbook!$D$1:$D$696,DashBoard!$B23) -> 0 | N23: =SUMIFS(Logbook!$F$1:$F$696,Logbook!$A$1:$A$696,DashBoard!N$4,Logbook!$D$1:$D$696,DashBoard!$B23) -> 0 | ... R23: =SUMIFS(Logbook!$F$1:$F$696,Logbook!$A$1:$A$696,DashBoard!R$4,Logbook!$D$1:$D$696,DashBoard!$B23) -> 0 | S23: =SUM(G23:R23) -> 435.59
B24: Dining Out | C24: =SUMIFS(Logbook!F$1:F$696,Logbook!A$1:A$696,DashBoard!$C$3,Logbook!D$1:D$696,DashBoard!B24) -> 423.44 | D24: 200 | E24: =SUM(D24-C24) -> -223.44 | G24: =SUMIFS(Logbook!$F$1:$F$696,Logbook!$A$1:$A$696,DashBoard!G$4,Logbook!$D$1:$D$696,DashBoard!$B24) -> 202.16 | H24: =SUMIFS(Logbook!$F$1:$F$696,Logbook!$A$1:$A$696,DashBoard!H$4,Logbook!$D$1:$D$696,DashBoard!$B24) -> 423.44 | I24: =SUMIFS(Logbook!$F$1:$F$696,Logbook!$A$1:$A$696,DashBoard!I$4,Logbook!$D$1:$D$696,DashBoard!$B24) -> 0 | J24: =SUMIFS(Logbook!$F$1:$F$696,Logbook!$A$1:$A$696,DashBoard!J$4,Logbook!$D$1:$D$696,DashBoard!$B24) -> 0 | K24: =SUMIFS(Logbook!$F$1:$F$696,Logbook!$A$1:$A$696,DashBoard!K$4,Logbook!$D$1:$D$696,DashBoard!$B24) -> 0 | L24: =SUMIFS(Logbook!$F$1:$F$696,Logbook!$A$1:$A$696,DashBoard!L$4,Logbook!$D$1:$D$696,DashBoard!$B24) -> 0 | M24: =SUMIFS(Logbook!$F$1:$F$696,Logbook!$A$1:$A$696,DashBoard!M$4,Logbook!$D$1:$D$696,DashBoard!$B24) -> 0 | N24: =SUMIFS(Logbook!$F$1:$F$696,Logbook!$A$1:$A$696,DashBoard!N$4,Logbook!$D$1:$D$696,DashBoard!$B24) -> 0 | ... R24: =SUMIFS(Logbook!$F$1:$F$696,Logbook!$A$1:$A$696,DashBoard!R$4,Logbook!$D$1:$D$696,DashBoard!$B24) -> 0 | S24: =SUM(G24:R24) -> 625.6
B25: Entertainment | C25: =SUMIFS(Logbook!F$1:F$696,Logbook!A$1:A$696,DashBoard!$C$3,Logbook!D$1:D$696,DashBoard!B25) -> 75 | D25: 150 | E25: =SUM(D25-C25) -> 75 | G25: =SUMIFS(Logbook!$F$1:$F$696,Logbook!$A$1:$A$696,DashBoard!G$4,Logbook!$D$1:$D$696,DashBoard!$B25) -> 310.6 | H25: =SUMIFS(Logbook!$F$1:$F$696,Logbook!$A$1:$A$696,DashBoard!H$4,Logbook!$D$1:$D$696,DashBoard!$B25) -> 75 | I25: =SUMIFS(Logbook!$F$1:$F$696,Logbook!$A$1:$A$696,DashBoard!I$4,Logbook!$D$1:$D$696,DashBoard!$B25) -> 0 | J25: =SUMIFS(Logbook!$F$1:$F$696,Logbook!$A$1:$A$696,DashBoard!J$4,Logbook!$D$1:$D$696,DashBoard!$B25) -> 0 | K25: =SUMIFS(Logbook!$F$1:$F$696,Logbook!$A$1:$A$696,DashBoard!K$4,Logbook!$D$1:$D$696,DashBoard!$B25) -> 0 | L25: =SUMIFS(Logbook!$F$1:$F$696,Logbook!$A$1:$A$696,DashBoard!L$4,Logbook!$D$1:$D$696,DashBoard!$B25) -> 0 | M25: =SUMIFS(Logbook!$F$1:$F$696,Logbook!$A$1:$A$696,DashBoard!M$4,Logbook!$D$1:$D$696,DashBoard!$B25) -> 0 | N25: =SUMIFS(Logbook!$F$1:$F$696,Logbook!$A$1:$A$696,DashBoard!N$4,Logbook!$D$1:$D$696,DashBoard!$B25) -> 0 | ... R25: =SUMIFS(Logbook!$F$1:$F$696,Logbook!$A$1:$A$696,DashBoard!R$4,Logbook!$D$1:$D$696,DashBoard!$B25) -> 0 | S25: =SUM(G25:R25) -> 385.6
B26: SAVINGS! | C26: =SUMIFS(Logbook!F$1:F$696,Logbook!A$1:A$696,DashBoard!$C$3,Logbook!D$1:D$696,DashBoard!B26) -> 6000 | E26: =C26 -> 6000 | G26: =SUMIFS(Logbook!$F$1:$F$696,Logbook!$A$1:$A$696,DashBoard!G$4,Logbook!$D$1:$D$696,DashBoard!$B26) -> 0 | H26: =SUMIFS(Logbook!$F$1:$F$696,Logbook!$A$1:$A$696,DashBoard!H$4,Logbook!$D$1:$D$696,DashBoard!$B26) -> 6000 | I26: =SUMIFS(Logbook!$F$1:$F$696,Logbook!$A$1:$A$696,DashBoard!I$4,Logbook!$D$1:$D$696,DashBoard!$B26) -> 0 | J26: =SUMIFS(Logbook!$F$1:$F$696,Logbook!$A$1:$A$696,DashBoard!J$4,Logbook!$D$1:$D$696,DashBoard!$B26) -> 0 | K26: =SUMIFS(Logbook!$F$1:$F$696,Logbook!$A$1:$A$696,DashBoard!K$4,Logbook!$D$1:$D$696,DashBoard!$B26) -> 0 | L26: =SUMIFS(Logbook!$F$1:$F$696,Logbook!$A$1:$A$696,DashBoard!L$4,Logbook!$D$1:$D$696,DashBoard!$B26) -> 0 | M26: =SUMIFS(Logbook!$F$1:$F$696,Logbook!$A$1:$A$696,DashBoard!M$4,Logbook!$D$1:$D$696,DashBoard!$B26) -> 0 | N26: =SUMIFS(Logbook!$F$1:$F$696,Logbook!$A$1:$A$696,DashBoard!N$4,Logbook!$D$1:$D$696,DashBoard!$B26) -> 0 | ... R26: =SUMIFS(Logbook!$F$1:$F$696,Logbook!$A$1:$A$696,DashBoard!R$4,Logbook!$D$1:$D$696,DashBoard!$B26) -> 0 | S26: =SUM(G26:R26) -> 6000
C27: =SUMIFS(Logbook!F$1:F$696,Logbook!A$1:A$696,DashBoard!$C$3,Logbook!D$1:D$696,DashBoard!B27) -> 0 | E27: =SUM(D27-C27) -> 0 | G27: =SUMIFS(Logbook!$F$1:$F$696,Logbook!$A$1:$A$696,DashBoard!G$4,Logbook!$D$1:$D$696,DashBoard!$B27) -> 0 | H27: =SUMIFS(Logbook!$F$1:$F$696,Logbook!$A$1:$A$696,DashBoard!H$4,Logbook!$D$1:$D$696,DashBoard!$B27) -> 0 | I27: =SUMIFS(Logbook!$F$1:$F$696,Logbook!$A$1:$A$696,DashBoard!I$4,Logbook!$D$1:$D$696,DashBoard!$B27) -> 0 | J27: =SUMIFS(Logbook!$F$1:$F$696,Logbook!$A$1:$A$696,DashBoard!J$4,Logbook!$D$1:$D$696,DashBoard!$B27) -> 0 | K27: =SUMIFS(Logbook!$F$1:$F$696,Logbook!$A$1:$A$696,DashBoard!K$4,Logbook!$D$1:$D$696,DashBoard!$B27) -> 0 | L27: =SUMIFS(Logbook!$F$1:$F$696,Logbook!$A$1:$A$696,DashBoard!L$4,Logbook!$D$1:$D$696,DashBoard!$B27) -> 0 | M27: =SUMIFS(Logbook!$F$1:$F$696,Logbook!$A$1:$A$696,DashBoard!M$4,Logbook!$D$1:$D$696,DashBoard!$B27) -> 0 | N27: =SUMIFS(Logbook!$F$1:$F$696,Logbook!$A$1:$A$696,DashBoard!N$4,Logbook!$D$1:$D$696,DashBoard!$B27) -> 0 | ... R27: =SUMIFS(Logbook!$F$1:$F$696,Logbook!$A$1:$A$696,DashBoard!R$4,Logbook!$D$1:$D$696,DashBoard!$B27) -> 0 | S27: =SUM(G27:R27) -> 0
C28: =SUMIFS(Logbook!F$1:F$696,Logbook!A$1:A$696,DashBoard!$C$3,Logbook!D$1:D$696,DashBoard!B28) -> 0 | E28: =SUM(D28-C28) -> 0 | G28: =SUMIFS(Logbook!$F$1:$F$696,Logbook!$A$1:$A$696,DashBoard!G$4,Logbook!$D$1:$D$696,DashBoard!$B28) -> 0 | H28: =SUMIFS(Logbook!$F$1:$F$696,Logbook!$A$1:$A$696,DashBoard!H$4,Logbook!$D$1:$D$696,DashBoard!$B28) -> 0 | I28: =SUMIFS(Logbook!$F$1:$F$696,Logbook!$A$1:$A$696,DashBoard!I$4,Logbook!$D$1:$D$696,DashBoard!$B28) -> 0 | J28: =SUMIFS(Logbook!$F$1:$F$696,Logbook!$A$1:$A$696,DashBoard!J$4,Logbook!$D$1:$D$696,DashBoard!$B28) -> 0 | K28: =SUMIFS(Logbook!$F$1:$F$696,Logbook!$A$1:$A$696,DashBoard!K$4,Logbook!$D$1:$D$696,DashBoard!$B28) -> 0 | L28: =SUMIFS(Logbook!$F$1:$F$696,Logbook!$A$1:$A$696,DashBoard!L$4,Logbook!$D$1:$D$696,DashBoard!$B28) -> 0 | M28: =SUMIFS(Logbook!$F$1:$F$696,Logbook!$A$1:$A$696,DashBoard!M$4,Logbook!$D$1:$D$696,DashBoard!$B28) -> 0 | N28: =SUMIFS(Logbook!$F$1:$F$696,Logbook!$A$1:$A$696,DashBoard!N$4,Logbook!$D$1:$D$696,DashBoard!$B28) -> 0 | ... R28: =SUMIFS(Logbook!$F$1:$F$696,Logbook!$A$1:$A$696,DashBoard!R$4,Logbook!$D$1:$D$696,DashBoard!$B28) -> 0 | S28: =SUM(G28:R28) -> 0
C29: =SUMIFS(Logbook!F$1:F$696,Logbook!A$1:A$696,DashBoard!$C$3,Logbook!D$1:D$696,DashBoard!B29) -> 0 | E29: =SUM(D29-C29) -> 0 | G29: =SUMIFS(Logbook!$F$1:$F$696,Logbook!$A$1:$A$696,DashBoard!G$4,Logbook!$D$1:$D$696,DashBoard!$B29) -> 0 | H29: =SUMIFS(Logbook!$F$1:$F$696,Logbook!$A$1:$A$696,DashBoard!H$4,Logbook!$D$1:$D$696,DashBoard!$B29) -> 0 | I29: =SUMIFS(Logbook!$F$1:$F$696,Logbook!$A$1:$A$696,DashBoard!I$4,Logbook!$D$1:$D$696,DashBoard!$B29) -> 0 | J29: =SUMIFS(Logbook!$F$1:$F$696,Logbook!$A$1:$A$696,DashBoard!J$4,Logbook!$D$1:$D$696,DashBoard!$B29) -> 0 | K29: =SUMIFS(Logbook!$F$1:$F$696,Logbook!$A$1:$A$696,DashBoard!K$4,Logbook!$D$1:$D$696,DashBoard!$B29) -> 0 | L29: =SUMIFS(Logbook!$F$1:$F$696,Logbook!$A$1:$A$696,DashBoard!L$4,Logbook!$D$1:$D$696,DashBoard!$B29) -> 0 | M29: =SUMIFS(Logbook!$F$1:$F$696,Logbook!$A$1:$A$696,DashBoard!M$4,Logbook!$D$1:$D$696,DashBoard!$B29) -> 0 | N29: =SUMIFS(Logbook!$F$1:$F$696,Logbook!$A$1:$A$696,DashBoard!N$4,Logbook!$D$1:$D$696,DashBoard!$B29) -> 0 | ... R29: =SUMIFS(Logbook!$F$1:$F$696,Logbook!$A$1:$A$696,DashBoard!R$4,Logbook!$D$1:$D$696,DashBoard!$B29) -> 0 | S29: =SUM(G29:R29) -> 0
C30: =SUMIFS(Logbook!F$1:F$696,Logbook!A$1:A$696,DashBoard!$C$3,Logbook!D$1:D$696,DashBoard!B30) -> 0 | E30: =SUM(D30-C30) -> 0 | G30: =SUMIFS(Logbook!$F$1:$F$696,Logbook!$A$1:$A$696,DashBoard!G$4,Logbook!$D$1:$D$696,DashBoard!$B30) -> 0 | H30: =SUMIFS(Logbook!$F$1:$F$696,Logbook!$A$1:$A$696,DashBoard!H$4,Logbook!$D$1:$D$696,DashBoard!$B30) -> 0 | I30: =SUMIFS(Logbook!$F$1:$F$696,Logbook!$A$1:$A$696,DashBoard!I$4,Logbook!$D$1:$D$696,DashBoard!$B30) -> 0 | J30: =SUMIFS(Logbook!$F$1:$F$696,Logbook!$A$1:$A$696,DashBoard!J$4,Logbook!$D$1:$D$696,DashBoard!$B30) -> 0 | K30: =SUMIFS(Logbook!$F$1:$F$696,Logbook!$A$1:$A$696,DashBoard!K$4,Logbook!$D$1:$D$696,DashBoard!$B30) -> 0 | L30: =SUMIFS(Logbook!$F$1:$F$696,Logbook!$A$1:$A$696,DashBoard!L$4,Logbook!$D$1:$D$696,DashBoard!$B30) -> 0 | M30: =SUMIFS(Logbook!$F$1:$F$696,Logbook!$A$1:$A$696,DashBoard!M$4,Logbook!$D$1:$D$696,DashBoard!$B30) -> 0 | N30: =SUMIFS(Logbook!$F$1:$F$696,Logbook!$A$1:$A$696,DashBoard!N$4,Logbook!$D$1:$D$696,DashBoard!$B30) -> 0 | ... R30: =SUMIFS(Logbook!$F$1:$F$696,Logbook!$A$1:$A$696,DashBoard!R$4,Logbook!$D$1:$D$696,DashBoard!$B30) -> 0 | S30: =SUM(G30:R30) -> 0
B31: Total Expenses | C31: =SUM(C14:C27) -> 13018.04 | D31: =SUM(D14:D30) -> 10500 | E31: =SUM(E14,E17,E18,E19,E20,E21,E22,E23,E24,E25,E27,E28,E29,E30,E15,E16) -> 3481.96 | F31: =SUM(F14,F17,F18,F19,F20,F21,F22,F23,F24,F25,F27,F28,F29,F30) -> 0 | G31: =SUM(G14,G17,G18,G19,G20,G21,G22,G23,G24,G25,G27,G28,G29,G30) -> 7560.88 | H31: =SUM(H14,H17,H18,H19,H20,H21,H22,H23,H24,H25,H27,H28,H29,H30) -> 7018.04 | I31: =SUM(I14,I17,I18,I19,I20,I21,I22,I23,I24,I25,I27,I28,I29,I30) -> 0 | J31: =SUM(J14,J17,J18,J19,J20,J21,J22,J23,J24,J25,J27,J28,J29,J30) -> 0 | K31: =SUM(K14,K17,K18,K19,K20,K21,K22,K23,K24,K25,K27,K28,K29,K30) -> 0 | L31: =SUM(L14,L17,L18,L19,L20,L21,L22,L23,L24,L25,L27,L28,L29,L30) -> 0 | M31: =SUM(M14,M17,M18,M19,M20,M21,M22,M23,M24,M25,M27,M28,M29,M30) -> 0 | ... S31: =SUM(S14,S17,S18,S19,S20,S21,S22,S23,S24,S25,S27,S28,S29,S30) -> 14578.92
B32: Total Expenses
B33: Total Expenses
G34: =G11-G31 -> 9912.04 | H34: =H11-H31 -> -2933.77 | I34: =I11-I31 -> 0 | J34: =J11-J31 -> 0 | K34: =K11-K31 -> 0 | L34: =L11-L31 -> 0 | M34: =M11-M31 -> 0 | N34: =N11-N31 -> 0 | ... S34: =S11-S31 -> 6978.27
S35: =SUM(S15,S16,S26) -> 8714

Sheet AUDITS
A1: Where? | B1: When? | C1: What? | D1: Details | E1: Who
A2: Logbook, Dashboard, Fireflyiii | B2: 46046 | C2: Complete | D2: Audited, reconcile purchases with balances | E2: Eric
A3: Logbook, Dashboard, Fireflyiii | B3: 46054 | C3: Complete | D3: Audited, reconcile purchases with balances | E3: Eric
A4: Confirm Navy Fed Matches | B4: 46059 | C4: Complete | D4: Ensure FF-iii, Log, and Statements Match | E4: Eric
A5: Confirm Navy Fed Matches | B5: 46063 | C5: Complete | D5: Ensure FF-iii, Log, and Statements Match | E5: Eric
A6: Confirm Navy Fed Matches | B6: 46067 | C6: Complete | D6: Ensure FF-iii, Log, and Statements Match | E6: Eric
